Data_Processing/ProcessData.py
Data_Processing/__init__.py
Data_extraction/DataExtract.py
Data_extraction/__init__.py
Data_Platforme-1.0.0.dist-info/METADATA
Data_Platforme-1.0.0.dist-info/WHEEL
Data_Platforme-1.0.0.dist-info/top_level.txt
Data_Platforme-1.0.0.dist-info/RECORD
