Metadata-Version: 2.1
Name: Data-Platforme
Version: 1.0.0
Summary: Data Platforme
Home-page: https://github.com/wafaait/DataPlateform
Author: wafa AIT DAOUD
Author-email: aitdaoudwafa@gmail.com
Classifier: Programming Language :: Python :: 3
Classifier: License :: OSI Approved :: MIT License
Classifier: Operating System :: OS Independent
